{
  "$schema": "https://schema.management.azure.com/schemas/2019-04-01/deploymentTemplate.json#",
  "contentVersion": "1.0.0.0",
  "Parameters": {
    "Workspace": {
      "type": "string"
    }
  },
  "resources": [
    {
      "id": "[concat(resourceId('Microsoft.OperationalInsights/workspaces/providers', parameters('workspace'), 'Microsoft.SecurityInsights'),'/alertRules/eff71000-f709-47a3-8007-e8a856db06e5')]",
      "name": "[concat(parameters('workspace'),'/Microsoft.SecurityInsights/eff71000-f709-47a3-8007-e8a856db06e5')]",
      "type": "Microsoft.OperationalInsights/workspaces/providers/alertRules",
      "kind": "Scheduled",
      "apiVersion": "2021-03-01-preview",
      "properties": {
        "suppressionEnabled": false,
        "status": "Available",
        "eventGroupingSettings": {
          "aggregationKind": "SingleAlert"
        },
        "queryPeriod": "5m",
        "query": "CBSLog_Azure_1_CL | where severity_s == \"Informational\" | where type_s == \"Breached Credential\" | where status_s != \"Closed\" or status_s != \"Resolved\"",
        "description": "New Breached Credential with severity Informational found",
        "triggerThreshold": 0,
        "triggerOperator": "gt",
        "severity": "Informational",
        "tactics": [
          "InitialAccess"
        ],
        "name": "Breached Credential (Informational)",
        "incidentConfiguration": {
          "groupingConfiguration": {
            "reopenClosedIncident": false,
            "matchingMethod": "AllEntities",
            "enabled": false,
            "lookbackDuration": "PT5H"
          },
          "createIncident": true
        },
        "queryFrequency": "5m",
        "suppressionDuration": "5h"
      }
    }
  ]
}
