{
  "$schema": "https://schema.management.azure.com/schemas/2019-04-01/deploymentTemplate.json#",
  "contentVersion": "1.0.0.0",
  "Parameters": {
    "Workspace": {
      "type": "string"
    }
  },
  "resources": [
    {
      "id": "[concat(resourceId('Microsoft.OperationalInsights/workspaces/providers', parameters('workspace'), 'Microsoft.SecurityInsights'),'/alertRules/fbcdc4ed-fe19-4d15-9e0f-7e27edd1370b')]",
      "name": "[concat(parameters('workspace'),'/Microsoft.SecurityInsights/fbcdc4ed-fe19-4d15-9e0f-7e27edd1370b')]",
      "type": "Microsoft.OperationalInsights/workspaces/providers/alertRules",
      "kind": "Scheduled",
      "apiVersion": "2021-03-01-preview",
      "properties": {
        "triggerThreshold": 0,
        "severity": "Medium",
        "suppressionDuration": "5h",
        "incidentConfiguration": {
          "groupingConfiguration": {
            "lookbackDuration": "PT5H",
            "reopenClosedIncident": false,
            "matchingMethod": "AllEntities",
            "enabled": false
          },
          "createIncident": true
        },
        "triggerOperator": "gt",
        "suppressionEnabled": false,
        "eventGroupingSettings": {
          "aggregationKind": "SingleAlert"
        },
        "tactics": [
          "DefenseEvasion"
        ],
        "queryFrequency": "5m",
        "status": "Available",
        "description": "New Trap 10 with severity Medium found",
        "query": "CBSLog_Azure_1_CL | where severity_s == \"Medium\" | where type_s == \"Trap 10\" | where status_s != \"Closed\" or status_s != \"Resolved\"",
        "queryPeriod": "5m",
        "name": "Trap 10 (Medium)"
      }
    }
  ]
}
