{
  "$schema": "https://schema.management.azure.com/schemas/2019-04-01/deploymentTemplate.json#",
  "contentVersion": "1.0.0.0",
  "Parameters": {
    "Workspace": {
      "type": "string"
    }
  },
  "resources": [
    {
      "id": "[concat(resourceId('Microsoft.OperationalInsights/workspaces/providers', parameters('workspace'), 'Microsoft.SecurityInsights'),'/alertRules/ca509c4b-d30f-4bad-b59c-4d0ddd0fc822')]",
      "name": "[concat(parameters('workspace'),'/Microsoft.SecurityInsights/ca509c4b-d30f-4bad-b59c-4d0ddd0fc822')]",
      "type": "Microsoft.OperationalInsights/workspaces/providers/alertRules",
      "kind": "Scheduled",
      "apiVersion": "2021-03-01-preview",
      "properties": {
        "customDetails": {
          "Remediation": "ShortRemediation",
          "Description": "ShortDescription"
        },
        "description": "BloodHound Attack Path Finding - Add Resource-Based Constrained Delegation Privileges on Tier Zero Computers",
        "queryFrequency": "1h",
        "name": "BloodHound Attack Path Finding - Add Resource-Based Constrained Delegation Privileges on Tier Zero Computers",
        "tactics": [],
        "query": "BHEAttackPathsData_CL | where Finding == \"T0AddAllowedToAct\"",
        "triggerThreshold": 0,
        "queryPeriod": "1h",
        "status": "Available",
        "severity": "Medium",
        "triggerOperator": "gt",
        "entityMappings": [
          {
            "entityType": "URL",
            "fieldMappings": [
              {
                "identifier": "Url",
                "columnName": "domain_name"
              }
            ]
          }
        ]
      }
    }
  ]
}
