{
  "$schema": "https://schema.management.azure.com/schemas/2019-04-01/deploymentTemplate.json#",
  "contentVersion": "1.0.0.0",
  "Parameters": {
    "Workspace": {
      "type": "string"
    }
  },
  "resources": [
    {
      "id": "[concat(resourceId('Microsoft.OperationalInsights/workspaces/providers', parameters('workspace'), 'Microsoft.SecurityInsights'),'/alertRules/1f9610b1-f9e0-4da2-9600-12f07ba6f437')]",
      "name": "[concat(parameters('workspace'),'/Microsoft.SecurityInsights/1f9610b1-f9e0-4da2-9600-12f07ba6f437')]",
      "type": "Microsoft.OperationalInsights/workspaces/providers/alertRules",
      "kind": "Scheduled",
      "apiVersion": "2021-03-01-preview",
      "properties": {
        "queryPeriod": "1h",
        "description": "BloodHound Attack Path Finding - AS-REP Roastable User Accounts",
        "severity": "Medium",
        "customDetails": {
          "Description": "ShortDescription",
          "Remediation": "ShortRemediation"
        },
        "entityMappings": [
          {
            "fieldMappings": [
              {
                "identifier": "Url",
                "columnName": "domain_name"
              }
            ],
            "entityType": "URL"
          }
        ],
        "triggerThreshold": 0,
        "queryFrequency": "1h",
        "status": "Available",
        "query": "BHEAttackPathsData_CL | where Finding == \"ASREPRoasting\"",
        "tactics": [],
        "triggerOperator": "gt",
        "name": "BloodHound Attack Path Finding - AS-REP Roastable User Accounts"
      }
    }
  ]
}
