{
  "$schema": "https://schema.management.azure.com/schemas/2019-04-01/deploymentTemplate.json#",
  "contentVersion": "1.0.0.0",
  "Parameters": {
    "Workspace": {
      "type": "string"
    }
  },
  "resources": [
    {
      "id": "[concat(resourceId('Microsoft.OperationalInsights/workspaces/providers', parameters('workspace'), 'Microsoft.SecurityInsights'),'/alertRules/645b0f09-f318-41c3-860d-6c0fb595af2b')]",
      "name": "[concat(parameters('workspace'),'/Microsoft.SecurityInsights/645b0f09-f318-41c3-860d-6c0fb595af2b')]",
      "type": "Microsoft.OperationalInsights/workspaces/providers/alertRules",
      "kind": "Scheduled",
      "apiVersion": "2021-03-01-preview",
      "properties": {
        "triggerOperator": "gt",
        "status": "Available",
        "severity": "Medium",
        "customDetails": {
          "Remediation": "ShortRemediation",
          "Description": "ShortDescription"
        },
        "description": "BloodHound Attack Path Finding - WriteOwnerLimitedRights Privileges on Tier Zero Objects",
        "triggerThreshold": 0,
        "entityMappings": [
          {
            "fieldMappings": [
              {
                "columnName": "domain_name",
                "identifier": "Url"
              }
            ],
            "entityType": "URL"
          }
        ],
        "tactics": [],
        "queryPeriod": "1h",
        "query": "BHEAttackPathsData_CL | where Finding == \"T0WriteOwnerLimitedRights\"",
        "queryFrequency": "1h",
        "name": "BloodHound Attack Path Finding - WriteOwnerLimitedRights Privileges on Tier Zero Objects"
      }
    }
  ]
}
