{
  "$schema": "https://schema.management.azure.com/schemas/2019-04-01/deploymentTemplate.json#",
  "contentVersion": "1.0.0.0",
  "Parameters": {
    "Workspace": {
      "type": "string"
    }
  },
  "resources": [
    {
      "id": "[concat(resourceId('Microsoft.OperationalInsights/workspaces/providers', parameters('workspace'), 'Microsoft.SecurityInsights'),'/alertRules/9c5b6d8f-3a02-4e9b-af4c-2d7e9b1f5a8c')]",
      "name": "[concat(parameters('workspace'),'/Microsoft.SecurityInsights/9c5b6d8f-3a02-4e9b-af4c-2d7e9b1f5a8c')]",
      "type": "Microsoft.OperationalInsights/workspaces/providers/alertRules",
      "kind": "Scheduled",
      "apiVersion": "2021-03-01-preview",
      "properties": {
        "alertDetailsOverride": {
          "alertSeverityColumnName": "SecurityPosture",
          "alertDisplayNameFormat": "Device Compliance Issue: {{SecurityPosture}} Risk on {{DevicePlatform}} Device",
          "alertTacticsColumnName": "SecurityPosture",
          "alertDescriptionFormat": "{{SecurityPosture}} posture with {{DeviceComplianceStatus}} compliance"
        },
        "severity": "Medium",
        "entityMappings": [
          {
            "entityType": "Account",
            "fieldMappings": [
              {
                "identifier": "FullName",
                "columnName": "DeviceEmailAddress"
              }
            ]
          },
          {
            "entityType": "Host",
            "fieldMappings": [
              {
                "identifier": "HostName",
                "columnName": "DeviceGuid"
              },
              {
                "identifier": "OSFamily",
                "columnName": "DevicePlatform"
              },
              {
                "identifier": "OSVersion",
                "columnName": "DeviceOSVersion"
              }
            ]
          }
        ],
        "suppressionDuration": "PT30M",
        "name": "Lookout - Device Compliance and Security Status Changes (v2)",
        "tactics": [
          "Discovery",
          "DefenseEvasion",
          "Persistence"
        ],
        "eventGroupingSettings": {
          "aggregationKind": "AlertPerResult"
        },
        "suppressionEnabled": false,
        "status": "Available",
        "queryFrequency": "10m",
        "queryPeriod": "30m",
        "triggerThreshold": 0,
        "customDetails": {
          "DeviceSecStatus": "DeviceSecurityStatus",
          "SecurityPosture": "SecurityPosture",
          "DeviceModel": "DeviceModel",
          "PlatformRisk": "PlatformRisk",
          "DevicePlatform": "DevicePlatform",
          "MDMIntegration": "MDMIntegrationStatus",
          "ComplianceReason": "ComplianceReason",
          "DeviceRiskScore": "DeviceRiskScore",
          "ClientSDKVersion": "ClientLookoutSDKVersion",
          "DevCompliance": "DeviceComplianceStatus",
          "DeviceManufacturer": "DeviceManufacturer"
        },
        "description": "'Monitors device compliance status changes and security posture degradation using Lookout Mobile Risk API v2 enhanced device fields. Detects devices becoming non-compliant, security status changes, and potential device compromise indicators with detailed device context and MDM integration data.'\n",
        "triggerOperator": "gt",
        "query": "LookoutEvents\n| where EventType == \"DEVICE\"\n| where DeviceComplianceStatus in (\"Non-Compliant\", \"Partial\") \n   or DeviceSecurityStatus in (\"THREATS_HIGH\", \"THREATS_MEDIUM\")\n   or ChangeType == \"UPDATE\"\n| extend \n    DeviceRiskScore = case(\n        DeviceSecurityStatus == \"THREATS_HIGH\", 9,\n        DeviceSecurityStatus == \"THREATS_MEDIUM\", 6,\n        DeviceSecurityStatus == \"THREATS_LOW\", 3,\n        DeviceComplianceStatus == \"Non-Compliant\", 7,\n        DeviceComplianceStatus == \"Partial\", 4,\n        1\n    ),\n    ComplianceReason = case(\n        isempty(DeviceCheckinTime), \"No Recent Check-in\",\n        DeviceActivationStatus != \"ACTIVE\", \"Inactive Device\",\n        isempty(ClientLookoutSDKVersion), \"Missing Security Client\",\n        \"Configuration Issue\"\n    ),\n    PlatformRisk = case(\n        DevicePlatform == \"ANDROID\" and DeviceOSVersion matches regex @\"^[1-9]\\..*\", \"Outdated Android\",\n        DevicePlatform == \"IOS\" and DeviceOSVersion matches regex @\"^1[0-4]\\..*\", \"Outdated iOS\",\n        DevicePlatform == \"UNKNOWN\", \"Unknown Platform\",\n        \"Current\"\n    )\n| extend MDMIntegrationStatus = case(\n    isnotempty(MDMConnectorId) and isnotempty(MDMExternalId), \"Fully Integrated\",\n    isnotempty(MDMConnectorId), \"Partial Integration\", \n    \"Not Integrated\"\n)\n| extend SecurityPosture = case(\n    DeviceRiskScore >= 8, \"Critical\",\n    DeviceRiskScore >= 6, \"High\",\n    DeviceRiskScore >= 4, \"Medium\",\n    \"Low\"\n)\n| project\n    TimeGenerated,\n    EventId,\n    DeviceGuid,\n    DevicePlatform,\n    DeviceOSVersion,\n    DeviceManufacturer,\n    DeviceModel,\n    DeviceEmailAddress,\n    DeviceActivationStatus,\n    DeviceSecurityStatus,\n    DeviceComplianceStatus,\n    DeviceRiskScore,\n    SecurityPosture,\n    ComplianceReason,\n    PlatformRisk,\n    DeviceCheckinTime,\n    DeviceActivatedAt,\n    DeviceDeactivatedAt,\n    DeviceGroupGuid,\n    ClientLookoutSDKVersion,\n    ClientOTAVersion,\n    ClientPackageName,\n    ClientPackageVersion,\n    MDMConnectorId,\n    MDMConnectorUuid,\n    MDMExternalId,\n    MDMIntegrationStatus,\n    ActorType,\n    ActorGuid,\n    ChangeType\n",
        "incidentConfiguration": {
          "groupingConfiguration": {
            "groupByAlertDetails": [
              "DeviceGuid"
            ],
            "lookbackDuration": "P1D",
            "reopenClosedIncident": false,
            "groupByCustomDetails": [
              "SecurityPosture",
              "DevicePlatform"
            ],
            "enabled": true,
            "groupByEntities": [
              "Account",
              "Host"
            ],
            "matchingMethod": "Selected"
          },
          "createIncident": true
        }
      }
    }
  ]
}
