{
  "$schema": "https://schema.management.azure.com/schemas/2019-04-01/deploymentTemplate.json#",
  "contentVersion": "1.0.0.0",
  "Parameters": {
    "Workspace": {
      "type": "string"
    }
  },
  "resources": [
    {
      "id": "[concat(resourceId('Microsoft.OperationalInsights/workspaces/providers', parameters('workspace'), 'Microsoft.SecurityInsights'),'/alertRules/176abf3c-392a-47bd-b565-a4ecfd0ff7ec')]",
      "name": "[concat(parameters('workspace'),'/Microsoft.SecurityInsights/176abf3c-392a-47bd-b565-a4ecfd0ff7ec')]",
      "type": "Microsoft.OperationalInsights/workspaces/providers/alertRules",
      "kind": "Scheduled",
      "apiVersion": "2021-03-01-preview",
      "properties": {
        "customDetails": {
          "ObjectId": "ObjectId",
          "TriggeredTime": "TriggeredTime",
          "TriggeredAlarmId": "TriggeredAlarmId",
          "ObjectType": "ObjectType",
          "Comment": "Comment",
          "ObjectName": "ObjectName",
          "Status": "Status",
          "Name": "Name",
          "PredefinedAlarmId": "PredefinedAlarmId",
          "VoneHostName": "VoneHostName",
          "Description": "Description"
        },
        "severity": "Medium",
        "query": "VeeamOneTriggeredAlarms_CL | where PredefinedAlarmId == 378",
        "triggerOperator": "gt",
        "status": "Available",
        "eventGroupingSettings": {
          "aggregationKind": "AlertPerResult"
        },
        "triggerThreshold": 0,
        "name": "Veeam ONE Job Disabled (Veeam Backup for Microsoft 365)",
        "queryPeriod": "3h",
        "description": "Detects when Veeam Backup for Microsoft 365 jobs are disabled.",
        "tactics": [],
        "queryFrequency": "3h"
      }
    }
  ]
}
