{
  "$schema": "https://schema.management.azure.com/schemas/2019-04-01/deploymentTemplate.json#",
  "contentVersion": "1.0.0.0",
  "Parameters": {
    "Workspace": {
      "type": "string"
    }
  },
  "resources": [
    {
      "id": "[concat(resourceId('Microsoft.OperationalInsights/workspaces/providers', parameters('workspace'), 'Microsoft.SecurityInsights'),'/alertRules/6117e317-4b90-4bcc-a71f-0c1f29d82ce3')]",
      "name": "[concat(parameters('workspace'),'/Microsoft.SecurityInsights/6117e317-4b90-4bcc-a71f-0c1f29d82ce3')]",
      "type": "Microsoft.OperationalInsights/workspaces/providers/alertRules",
      "kind": "Scheduled",
      "apiVersion": "2021-03-01-preview",
      "properties": {
        "queryFrequency": "5m",
        "tactics": [],
        "severity": "High",
        "customDetails": {
          "ObjectId": "ObjectId",
          "ObjectName": "ObjectName",
          "Comment": "Comment",
          "TriggeredAlarmId": "TriggeredAlarmId",
          "VoneHostName": "VoneHostName",
          "Status": "Status",
          "Name": "Name",
          "PredefinedAlarmId": "PredefinedAlarmId",
          "TriggeredTime": "TriggeredTime",
          "ObjectType": "ObjectType",
          "Description": "Description"
        },
        "triggerThreshold": 0,
        "triggerOperator": "gt",
        "eventGroupingSettings": {
          "aggregationKind": "AlertPerResult"
        },
        "query": "VeeamOneTriggeredAlarms_CL | where PredefinedAlarmId == 332",
        "queryPeriod": "5m",
        "description": "Detects Hyper-V VMs with no replica configured.",
        "name": "Veeam ONE VM with No Replica (Hyper-V)",
        "status": "Available"
      }
    }
  ]
}
