{
  "$schema": "https://schema.management.azure.com/schemas/2019-04-01/deploymentTemplate.json#",
  "contentVersion": "1.0.0.0",
  "Parameters": {
    "Workspace": {
      "type": "string"
    }
  },
  "resources": [
    {
      "id": "[concat(resourceId('Microsoft.OperationalInsights/workspaces/providers', parameters('workspace'), 'Microsoft.SecurityInsights'),'/alertRules/f3c25011-4509-41c8-be27-35d891531c39')]",
      "name": "[concat(parameters('workspace'),'/Microsoft.SecurityInsights/f3c25011-4509-41c8-be27-35d891531c39')]",
      "type": "Microsoft.OperationalInsights/workspaces/providers/alertRules",
      "kind": "Scheduled",
      "apiVersion": "2021-03-01-preview",
      "properties": {
        "tactics": [
          "CredentialAccess",
          "Exfiltration",
          "Discovery"
        ],
        "triggerThreshold": 0,
        "eventGroupingSettings": {
          "aggregationKind": "AlertPerResult"
        },
        "customDetails": {
          "BB_Repository": "BB_Repository",
          "BB_Email": "BB_Email",
          "BB_DetectorName": "BB_DetectorName",
          "Service": "Service",
          "BB_RotationGuide": "BB_RotationGuide",
          "BB_Verified": "BB_Verified",
          "BB_Raw": "BB_Raw",
          "BB_Commit": "BB_Commit",
          "AlertID": "AlertID",
          "BB_Line": "BB_Line",
          "BB_File": "BB_File",
          "BB_Link": "BB_Link",
          "Status": "Status",
          "MappedSeverity": "Severity"
        },
        "incidentConfiguration": {
          "createIncident": true,
          "groupingConfiguration": {
            "enabled": false,
            "reopenClosedIncident": false,
            "lookbackDuration": "PT5H",
            "matchingMethod": "AllEntities"
          }
        },
        "queryPeriod": "30m",
        "query": "Alerts_bit_bucket \n| where Service == \"bit_bucket\" \n| extend MappedSeverity = Severity\n",
        "triggerOperator": "GreaterThan",
        "alertDetailsOverride": {
          "alertDescriptionFormat": "A sensitive secret was detected in Bitbucket repository {{BB_Repository}}. File {{BB_File}}:{{BB_Line}}. Investigator should verify exposure, rotate credentials and remediate impacted systems.\n",
          "alertDisplayNameFormat": "Secret Exposure in Bitbucket {{BB_File}} ({{BB_DetectorName}})"
        },
        "entityMappings": [
          {
            "fieldMappings": [
              {
                "identifier": "Url",
                "columnName": "BB_Repository"
              }
            ],
            "entityType": "Url"
          },
          {
            "fieldMappings": [
              {
                "identifier": "Url",
                "columnName": "BB_Link"
              }
            ],
            "entityType": "Url"
          },
          {
            "fieldMappings": [
              {
                "identifier": "Name",
                "columnName": "BB_File"
              },
              {
                "identifier": "Directory",
                "columnName": "KeywordName"
              }
            ],
            "entityType": "File"
          }
        ],
        "description": "'Detects exposed secrets in Bitbucket repositories using the Alerts_bit_bucket parser. Creates one incident per matched secret. Includes decoder, detector, commit, file, and repository context for SOC triage.'\n",
        "name": "Cyble Vision Alerts Bitbucket",
        "status": "Available",
        "severity": "Low",
        "queryFrequency": "30m",
        "enabled": true
      }
    }
  ]
}
