{
  "$schema": "https://schema.management.azure.com/schemas/2019-04-01/deploymentTemplate.json#",
  "contentVersion": "1.0.0.0",
  "Parameters": {
    "Workspace": {
      "type": "string"
    }
  },
  "resources": [
    {
      "id": "[concat(resourceId('Microsoft.OperationalInsights/workspaces/providers', parameters('workspace'), 'Microsoft.SecurityInsights'),'/alertRules/33B07EAA-F451-4C38-AC9F-8AF3F7E99F0E')]",
      "name": "[concat(parameters('workspace'),'/Microsoft.SecurityInsights/33B07EAA-F451-4C38-AC9F-8AF3F7E99F0E')]",
      "type": "Microsoft.OperationalInsights/workspaces/providers/alertRules",
      "kind": "Scheduled",
      "apiVersion": "2021-03-01-preview",
      "properties": {
        "triggerThreshold": 0,
        "name": "Cyble Vision Alerts Compromised Endpoint Cookies",
        "queryfrequency": "30m",
        "description": "'Detects compromised browser cookies associated with monitored entities. Identifies exposed authentication cookies with future expiry, enabling potential session hijacking or persistent unauthorized access.'\n",
        "customDetails": {
          "CookieExpiry": "CEC_Expiry",
          "MappedSeverity": "Severity",
          "CookieURL": "CEC_URL",
          "Status": "Status",
          "CookieEmail": "CEC_Email",
          "CookieDomain": "CEC_EmailDomain",
          "Service": "Service",
          "CookieSessionID": "CEC_SessionID",
          "AlertID": "AlertID"
        },
        "eventGroupingSettings": {
          "aggregationKind": "AlertPerResult"
        },
        "triggerOperator": "GreaterThan",
        "enabled": true,
        "queryPeriod": "30m",
        "query": "Alerts_compromised_endpoints_cookies\n| where Service == \"compromised_endpoints_cookies\"\n| extend MappedSeverity = Severity\n",
        "suppressionDuration": "PT1H",
        "severity": "Low",
        "incidentConfiguration": {
          "createIncident": true,
          "groupingConfiguration": {
            "matchingMethod": "AllEntities",
            "reopenClosedIncident": false,
            "lookbackDuration": "PT5H",
            "enabled": false
          }
        },
        "entityMappings": [
          {
            "entityType": "Url",
            "fieldMappings": [
              {
                "columnName": "CEC_URL",
                "identifier": "Url"
              }
            ]
          },
          {
            "entityType": "Account",
            "fieldMappings": [
              {
                "columnName": "CEC_Email",
                "identifier": "FullName"
              }
            ]
          }
        ],
        "status": "Available",
        "alertDetailsOverride": {
          "alertDisplayNameFormat": "Compromised Session Cookie {{CEC_Email}} {{CEC_URL}}",
          "alertDescriptionFormat": "A compromised browser session cookie associated with {{CEC_EmailDomain}} was detected for service {{CEC_URL}}. The cookie has not expired and may allow session hijacking. Session ID {{CEC_SessionID}}.\n"
        },
        "tactics": [
          "CredentialAccess",
          "DefenseEvasion"
        ]
      }
    }
  ]
}
