{
  "$schema": "https://schema.management.azure.com/schemas/2019-04-01/deploymentTemplate.json#",
  "contentVersion": "1.0.0.0",
  "Parameters": {
    "Workspace": {
      "type": "string"
    }
  },
  "resources": [
    {
      "id": "[concat(resourceId('Microsoft.OperationalInsights/workspaces/providers', parameters('workspace'), 'Microsoft.SecurityInsights'),'/alertRules/6d55fefc-b334-4b79-b11c-667746b5bdde')]",
      "name": "[concat(parameters('workspace'),'/Microsoft.SecurityInsights/6d55fefc-b334-4b79-b11c-667746b5bdde')]",
      "type": "Microsoft.OperationalInsights/workspaces/providers/alertRules",
      "kind": "Scheduled",
      "apiVersion": "2021-03-01-preview",
      "properties": {
        "alertDetailsOverride": {
          "alertDescriptionFormat": "A potentially suspicious mobile application was detected. Developer {{MA_Developer}} Market {{MA_MarketSource}} Deep Link {{MA_DeepLink}}\\n\n",
          "alertDynamicProperties": [],
          "alertDisplayNameFormat": "CybleVision Suspicious Mobile App {{MA_Title}}"
        },
        "severity": "Low",
        "entityMappings": [
          {
            "fieldMappings": [
              {
                "columnName": "MA_DeepLink",
                "identifier": "Url"
              }
            ],
            "entityType": "URL"
          },
          {
            "fieldMappings": [
              {
                "columnName": "Domain",
                "identifier": "DomainName"
              }
            ],
            "entityType": "DNS"
          }
        ],
        "description": "'Detects suspicious, unauthorized or impersonating mobile applications from 3rd-party marketplaces using CybleVision data. Extracts metadata, screenshots, developer, package name, and detailed app attributes.'\n",
        "customDetails": {
          "PackageName": "MA_PackageName",
          "MarketUpdated": "MA_MarketUpdated",
          "Description": "MA_Description",
          "Service": "Service",
          "MarketURL": "MA_MarketURL",
          "MappedSeverity": "Severity",
          "Status": "Status",
          "Screenshots": "MA_Screenshots",
          "CreatedOn": "MA_Created",
          "Website": "MA_Website",
          "MarketSource": "MA_MarketSource",
          "MarketStatus": "MA_MarketStatus",
          "Version": "MA_Version",
          "Tags": "MA_Tags",
          "Downloads": "MA_Downloads",
          "IconURL": "MA_MarketURL",
          "AlertID": "AlertID",
          "AppName": "AppName",
          "Developer": "MA_Developer",
          "AppEmail": "MA_Email"
        },
        "name": "CybleVision Alerts Mobile Apps",
        "status": "Available",
        "triggerOperator": "GreaterThan",
        "incidentConfiguration": {
          "groupingConfiguration": {
            "matchingMethod": "AllEntities",
            "lookbackDuration": "PT5H",
            "enabled": false,
            "reopenClosedIncident": false
          },
          "createIncident": true
        },
        "eventGroupingSettings": {
          "aggregationKind": "AlertPerResult"
        },
        "queryFrequency": "30m",
        "query": "Alerts_mobile_apps \n| where Service == \"mobile_apps\" \n| extend MappedSeverity = Severity\n",
        "subTechniques": [],
        "queryPeriod": "30m",
        "suppressionDuration": "PT5H",
        "enabled": true,
        "triggerThreshold": 0,
        "tactics": [
          "Reconnaissance",
          "ResourceDevelopment",
          "InitialAccess"
        ]
      }
    }
  ]
}
