{
  "$schema": "https://schema.management.azure.com/schemas/2019-04-01/deploymentTemplate.json#",
  "contentVersion": "1.0.0.0",
  "Parameters": {
    "Workspace": {
      "type": "string"
    }
  },
  "resources": [
    {
      "id": "[concat(resourceId('Microsoft.OperationalInsights/workspaces/providers', parameters('workspace'), 'Microsoft.SecurityInsights'),'/alertRules/b78c4641-cc16-48e0-9d05-c9b36a55d214')]",
      "name": "[concat(parameters('workspace'),'/Microsoft.SecurityInsights/b78c4641-cc16-48e0-9d05-c9b36a55d214')]",
      "type": "Microsoft.OperationalInsights/workspaces/providers/alertRules",
      "kind": "Scheduled",
      "apiVersion": "2021-03-01-preview",
      "properties": {
        "suppressionDuration": "PT5H",
        "tactics": [
          "Reconnaissance",
          "ResourceDevelopment",
          "Exfiltration"
        ],
        "description": "'Detects discussions, marketplace posts, threat actor activity, and intelligence mentions from cybercrime forums. Extracts discussion metadata, topic details, URLs, emails, phone numbers, and content using Alerts_CyberCrimeForums parser.'\n",
        "alertDetailsOverride": {
          "alertDescriptionFormat": "A mention was detected on a cybercrime forum. Source {{CF_SourceName}} By {{CF_DiscussionBy}} Content {{CF_Content}}\n",
          "alertDynamicProperties": [],
          "alertDisplayNameFormat": "CybleVision Forum Mention {{CF_TopicName}}"
        },
        "status": "Available",
        "name": "CybleVision Alerts Cyber Crime Forum Alerts",
        "queryPeriod": "30m",
        "triggerOperator": "GreaterThan",
        "enabled": true,
        "incidentConfiguration": {
          "groupingConfiguration": {
            "enabled": false,
            "matchingMethod": "AllEntities",
            "reopenClosedIncident": false,
            "lookbackDuration": "PT5H"
          },
          "createIncident": true
        },
        "eventGroupingSettings": {
          "aggregationKind": "AlertPerResult"
        },
        "severity": "Low",
        "queryFrequency": "30m",
        "subTechniques": [],
        "customDetails": {
          "TopicURL": "CF_TopicURL",
          "Likes": "CF_Likes",
          "TopicCreatedBy": "CF_TopicCreatedBy",
          "DiscussionBy": "CF_DiscussionBy",
          "MappedSeverity": "Severity",
          "Status": "Status",
          "TopicName": "CF_TopicName",
          "Content": "CF_Content",
          "Service": "Service",
          "Phones": "CF_Phones",
          "TopicID": "CF_TopicID",
          "Reputation": "CF_Reputation",
          "DiscussionDate": "CF_DiscussionDate",
          "AlertID": "AlertID",
          "Tags": "CF_Tags"
        },
        "entityMappings": [
          {
            "entityType": "Account",
            "fieldMappings": [
              {
                "identifier": "Name",
                "columnName": "CF_Emails"
              }
            ]
          },
          {
            "entityType": "URL",
            "fieldMappings": [
              {
                "identifier": "Url",
                "columnName": "CF_Urls"
              }
            ]
          },
          {
            "entityType": "DNS",
            "fieldMappings": [
              {
                "identifier": "DomainName",
                "columnName": "CF_SourceName"
              }
            ]
          }
        ],
        "triggerThreshold": 0,
        "query": "Alerts_cyber_crime_forums \n| where Service == \"cyber_crime_forums\" \n| extend MappedSeverity = Severity\n"
      }
    }
  ]
}
