{
  "$schema": "https://schema.management.azure.com/schemas/2019-04-01/deploymentTemplate.json#",
  "contentVersion": "1.0.0.0",
  "Parameters": {
    "Workspace": {
      "type": "string"
    }
  },
  "resources": [
    {
      "id": "[concat(resourceId('Microsoft.OperationalInsights/workspaces/providers', parameters('workspace'), 'Microsoft.SecurityInsights'),'/alertRules/1e7c8d9f-1d42-42b3-b6ce-12a637e05f16')]",
      "name": "[concat(parameters('workspace'),'/Microsoft.SecurityInsights/1e7c8d9f-1d42-42b3-b6ce-12a637e05f16')]",
      "type": "Microsoft.OperationalInsights/workspaces/providers/alertRules",
      "kind": "Scheduled",
      "apiVersion": "2021-03-01-preview",
      "properties": {
        "entityMappings": [
          {
            "fieldMappings": [
              {
                "identifier": "Address",
                "columnName": "IPRS_IP"
              }
            ],
            "entityType": "IP"
          }
        ],
        "query": "Alerts_ip_risk_score  \n| where Service == \"ip_risk_score\" \n| extend MappedSeverity = Severity\n",
        "name": "Cyble Vision Alerts IP Risk Score",
        "incidentConfiguration": {
          "alertDescriptionFormat": "The risk score for IP {{IPRS_IP}} has increased. Previous score {{IPRS_OldScore}}. New score {{IPRS_NewScore}}. This may represent newly observed malicious activity or updated threat intelligence.\n",
          "alertDisplayNameFormat": "Risk Score Increased for IP {{IPRS_IP}}",
          "groupingConfiguration": {
            "reopenClosedIncident": false,
            "enabled": false,
            "matchingMethod": "AllEntities",
            "lookbackDuration": "PT5H"
          },
          "alertDetailsOverride": null,
          "createIncident": true
        },
        "tactics": [
          "Reconnaissance"
        ],
        "triggerOperator": "GreaterThan",
        "severity": "Low",
        "triggerThreshold": 0,
        "eventGroupingSettings": {
          "aggregationKind": "AlertPerResult"
        },
        "queryfrequency": "30m",
        "enabled": true,
        "queryPeriod": "30m",
        "status": "Available",
        "customDetails": {
          "IPRS_IP": "IPRS_IP",
          "IPRS_NewScore": "IPRS_NewScore",
          "AlertID": "AlertID",
          "Service": "Service",
          "MappedSeverity": "Severity",
          "Status": "Status",
          "IPRS_OldScore": "IPRS_OldScore"
        },
        "description": "'Triggers when the risk score for a monitored IP increases significantly. This may indicate new malicious behavior or updated threat intelligence classification.'\n"
      }
    }
  ]
}
